{
  "id": 696,
  "idMal": 696,
  "title": {
    "native": "天地無用！",
    "romaji": "Tenchi Muyou!",
    "english": "Tenchi Muyo! Tenchi Universe"
  },
  "type": "ANIME",
  "format": "TV",
  "status": "FINISHED",
  "description": "Tenchi Masaki may be a 17-year-old young man in rural Japan, but little does he know how bad his day will be getting. When a space pirate chased by a pair of Galaxy Police officers crash-lands at his grandfather's temple, Tenchi is sucked into a new adventure that will literally blast him off into outer space and beyond. <br><br>\n(Source: Anime News Network)",
  "startDate": {
    "year": 1995,
    "month": 4,
    "day": 2
  },
  "endDate": {
    "year": 1995,
    "month": 9,
    "day": 24
  },
  "season": "SPRING",
  "seasonYear": 1995,
  "seasonInt": 952,
  "episodes": 26,
  "duration": 23,
  "chapters": null,
  "volumes": null,
  "countryOfOrigin": "JP",
  "isLicensed": true,
  "source": "ORIGINAL",
  "hashtag": null,
  "trailer": {
    "id": "G350vJSKH1U",
    "site": "youtube",
    "thumbnail": "https://i.ytimg.com/vi/G350vJSKH1U/hqdefault.jpg"
  },
  "updatedAt": 1748899330,
  "coverImage": {
    "extraLarge": "https://s4.anilist.co/file/anilistcdn/media/anime/cover/large/bx696-q40thYobzxmz.jpg",
    "large": "https://s4.anilist.co/file/anilistcdn/media/anime/cover/medium/bx696-q40thYobzxmz.jpg",
    "medium": "https://s4.anilist.co/file/anilistcdn/media/anime/cover/small/bx696-q40thYobzxmz.jpg",
    "color": "#f16b00"
  },
  "bannerImage": "https://s4.anilist.co/file/anilistcdn/media/anime/banner/696-d3QphXIJN64c.jpg",
  "genres": [
    "Comedy",
    "Romance",
    "Sci-Fi"
  ],
  "synonyms": [],
  "averageScore": 71,
  "meanScore": 71,
  "popularity": 15875,
  "favourites": 259,
  "tags": [
    {
      "id": 63,
      "name": "Space",
      "description": "Partly or completely set in outer space.",
      "category": "Setting-Universe",
      "rank": 84,
      "isGeneralSpoiler": false,
      "isMediaSpoiler": false,
      "isAdult": false
    },
    {
      "id": 780,
      "name": "Ojou-sama",
      "description": "Features a wealthy, high-class, oftentimes stuck up and demanding female character.",
      "category": "Cast-Traits",
      "rank": 80,
      "isGeneralSpoiler": false,
      "isMediaSpoiler": false,
      "isAdult": false
    },
    {
      "id": 139,
      "name": "Love Triangle",
      "description": "Centered around romantic feelings between more than two people. Includes all love polygons.",
      "category": "Theme-Romance",
      "rank": 79,
      "isGeneralSpoiler": false,
      "isMediaSpoiler": false,
      "isAdult": false
    },
    {
      "id": 1045,
      "name": "Heterosexual",
      "description": "Prominently features a romance between a man and a woman, not inherently sexual.",
      "category": "Theme-Romance",
      "rank": 79,
      "isGeneralSpoiler": false,
      "isMediaSpoiler": false,
      "isAdult": false
    },
    {
      "id": 191,
      "name": "Aliens",
      "description": "Prominently features extraterrestrial lifeforms.",
      "category": "Cast-Traits",
      "rank": 73,
      "isGeneralSpoiler": false,
      "isMediaSpoiler": false,
      "isAdult": false
    },
    {
      "id": 40,
      "name": "Police",
      "description": "Centers around the life and activities of law enforcement officers.",
      "category": "Theme-Other-Organisations",
      "rank": 68,
      "isGeneralSpoiler": false,
      "isMediaSpoiler": false,
      "isAdult": false
    },
    {
      "id": 23,
      "name": "Female Harem",
      "description": "Main cast features the protagonist plus several female characters who are romantically interested in them.",
      "category": "Theme-Romance",
      "rank": 60,
      "isGeneralSpoiler": false,
      "isMediaSpoiler": false,
      "isAdult": false
    },
    {
      "id": 356,
      "name": "Gyaru",
      "description": "Prominently features a female character who has a distinct American-emulated fashion style, such as tanned skin, bleached hair, and excessive makeup. Also known as gal.",
      "category": "Cast-Traits",
      "rank": 60,
      "isGeneralSpoiler": false,
      "isMediaSpoiler": false,
      "isAdult": false
    },
    {
      "id": 99,
      "name": "Henshin",
      "description": "Prominently features character or costume transformations which often grant special abilities.",
      "category": "Theme-Fantasy",
      "rank": 60,
      "isGeneralSpoiler": false,
      "isMediaSpoiler": false,
      "isAdult": false
    },
    {
      "id": 82,
      "name": "Male Protagonist",
      "description": "Main character is male.",
      "category": "Cast-Main Cast",
      "rank": 60,
      "isGeneralSpoiler": false,
      "isMediaSpoiler": false,
      "isAdult": false
    },
    {
      "id": 86,
      "name": "Primarily Female Cast",
      "description": "Main cast is mostly composed of female characters.",
      "category": "Cast-Main Cast",
      "rank": 60,
      "isGeneralSpoiler": false,
      "isMediaSpoiler": false,
      "isAdult": false
    },
    {
      "id": 226,
      "name": "Fugitive",
      "description": "Prominently features a character evading capture by an individual or organization.",
      "category": "Theme-Action",
      "rank": 46,
      "isGeneralSpoiler": false,
      "isMediaSpoiler": false,
      "isAdult": false
    },
    {
      "id": 46,
      "name": "School",
      "description": "Partly or completely set in a primary or secondary educational institution.",
      "category": "Setting-Scene",
      "rank": 20,
      "isGeneralSpoiler": false,
      "isMediaSpoiler": false,
      "isAdult": false
    },
    {
      "id": 220,
      "name": "Ghost",
      "description": "Prominently features a character who is a ghost.",
      "category": "Cast-Traits",
      "rank": 20,
      "isGeneralSpoiler": false,
      "isMediaSpoiler": true,
      "isAdult": false
    }
  ],
  "relations": {
    "edges": [
      {
        "node": {
          "id": 1006,
          "title": {
            "native": "天地無用! in Love"
          }
        },
        "relationType": "SEQUEL"
      },
      {
        "node": {
          "id": 539,
          "title": {
            "native": "天地無用! 魎皇鬼 第1期"
          }
        },
        "relationType": "ALTERNATIVE"
      },
      {
        "node": {
          "id": 20726,
          "title": {
            "native": "愛・天地無用!"
          }
        },
        "relationType": "OTHER"
      },
      {
        "node": {
          "id": 1918,
          "title": {
            "native": "魔法少女プリティサミー"
          }
        },
        "relationType": "SPIN_OFF"
      },
      {
        "node": {
          "id": 1101,
          "title": {
            "native": "天地無用！真夏のイヴ"
          }
        },
        "relationType": "SIDE_STORY"
      },
      {
        "node": {
          "id": 5781,
          "title": {
            "native": "異世界の聖機師物語"
          }
        },
        "relationType": "SPIN_OFF"
      }
    ]
  },
  "characters": {
    "edges": [
      {
        "role": "SUPPORTING",
        "node": {
          "id": 15682,
          "name": {
            "first": "Kagato",
            "last": "Jurai",
            "native": "神我人",
            "alternative": []
          },
          "image": {
            "large": "https://s4.anilist.co/file/anilistcdn/character/large/15682.jpg",
            "medium": "https://s4.anilist.co/file/anilistcdn/character/medium/15682.jpg"
          },
          "siteUrl": "https://anilist.co/character/15682"
        },
        "voiceActors": [
          {
            "id": 95084,
            "name": {
              "first": "Norio",
              "last": "Wakamoto",
              "native": "若本規夫"
            },
            "language": "JAPANESE",
            "image": {
              "large": "https://s4.anilist.co/file/anilistcdn/staff/large/n95084-RTrZSU38POPF.png",
              "medium": "https://s4.anilist.co/file/anilistcdn/staff/medium/n95084-RTrZSU38POPF.png"
            },
            "siteUrl": "https://anilist.co/staff/95084"
          }
        ]
      },
      {
        "role": "SUPPORTING",
        "node": {
          "id": 6670,
          "name": {
            "first": "Nobuyuki",
            "last": "Masaki",
            "native": "柾木信幸",
            "alternative": []
          },
          "image": {
            "large": "https://s4.anilist.co/file/anilistcdn/character/large/6670.jpg",
            "medium": "https://s4.anilist.co/file/anilistcdn/character/medium/6670.jpg"
          },
          "siteUrl": "https://anilist.co/character/6670"
        },
        "voiceActors": [
          {
            "id": 95142,
            "name": {
              "first": "Takeshi",
              "last": "Aono",
              "native": "青野武"
            },
            "language": "JAPANESE",
            "image": {
              "large": "https://s4.anilist.co/file/anilistcdn/staff/large/n95142-73E1XmGOOmhG.png",
              "medium": "https://s4.anilist.co/file/anilistcdn/staff/medium/n95142-73E1XmGOOmhG.png"
            },
            "siteUrl": "https://anilist.co/staff/95142"
          }
        ]
      },
      {
        "role": "SUPPORTING",
        "node": {
          "id": 6671,
          "name": {
            "first": "Katsuhito",
            "last": "Masaki",
            "native": "柾木勝仁",
            "alternative": [
              "Yōshō"
            ]
          },
          "image": {
            "large": "https://s4.anilist.co/file/anilistcdn/character/large/6671.jpg",
            "medium": "https://s4.anilist.co/file/anilistcdn/character/medium/6671.jpg"
          },
          "siteUrl": "https://anilist.co/character/6671"
        },
        "voiceActors": [
          {
            "id": 95142,
            "name": {
              "first": "Takeshi",
              "last": "Aono",
              "native": "青野武"
            },
            "language": "JAPANESE",
            "image": {
              "large": "https://s4.anilist.co/file/anilistcdn/staff/large/n95142-73E1XmGOOmhG.png",
              "medium": "https://s4.anilist.co/file/anilistcdn/staff/medium/n95142-73E1XmGOOmhG.png"
            },
            "siteUrl": "https://anilist.co/staff/95142"
          }
        ]
      },
      {
        "role": "SUPPORTING",
        "node": {
          "id": 20010,
          "name": {
            "first": "Ken-Ohki",
            "last": null,
            "native": "眷皇鬼",
            "alternative": []
          },
          "image": {
            "large": "https://s4.anilist.co/file/anilistcdn/character/large/20010.jpg",
            "medium": "https://s4.anilist.co/file/anilistcdn/character/medium/20010.jpg"
          },
          "siteUrl": "https://anilist.co/character/20010"
        },
        "voiceActors": [
          {
            "id": 95148,
            "name": {
              "first": "Aki",
              "last": "Uechi",
              "native": "うえちあき"
            },
            "language": "JAPANESE",
            "image": {
              "large": "https://s4.anilist.co/file/anilistcdn/staff/large/n95148-JiNi79wg9ScS.png",
              "medium": "https://s4.anilist.co/file/anilistcdn/staff/medium/n95148-JiNi79wg9ScS.png"
            },
            "siteUrl": "https://anilist.co/staff/95148"
          }
        ]
      },
      {
        "role": "MAIN",
        "node": {
          "id": 5721,
          "name": {
            "first": "Sasami",
            "last": "Masaki Jurai",
            "native": "柾木砂沙美樹雷",
            "alternative": [
              "Sasami Kawai (河合砂沙美)",
              "Pretty Sammy"
            ]
          },
          "image": {
            "large": "https://s4.anilist.co/file/anilistcdn/character/large/5721.jpg",
            "medium": "https://s4.anilist.co/file/anilistcdn/character/medium/5721.jpg"
          },
          "siteUrl": "https://anilist.co/character/5721"
        },
        "voiceActors": [
          {
            "id": 95904,
            "name": {
              "first": "Chisa",
              "last": "Yokoyama",
              "native": "横山智佐"
            },
            "language": "JAPANESE",
            "image": {
              "large": "https://s4.anilist.co/file/anilistcdn/staff/large/n95904-Hwjlrw4tCDMl.png",
              "medium": "https://s4.anilist.co/file/anilistcdn/staff/medium/n95904-Hwjlrw4tCDMl.png"
            },
            "siteUrl": "https://anilist.co/staff/95904"
          }
        ]
      },
      {
        "role": "MAIN",
        "node": {
          "id": 6514,
          "name": {
            "first": "Kiyone",
            "last": "Makibi",
            "native": "真備清音",
            "alternative": []
          },
          "image": {
            "large": "https://s4.anilist.co/file/anilistcdn/character/large/6514.jpg",
            "medium": "https://s4.anilist.co/file/anilistcdn/character/medium/6514.jpg"
          },
          "siteUrl": "https://anilist.co/character/6514"
        },
        "voiceActors": [
          {
            "id": 95290,
            "name": {
              "first": "Yuri",
              "last": "Amano",
              "native": "天野由梨"
            },
            "language": "JAPANESE",
            "image": {
              "large": "https://s4.anilist.co/file/anilistcdn/staff/large/n95290-nU8h5vWr8RCv.jpg",
              "medium": "https://s4.anilist.co/file/anilistcdn/staff/medium/n95290-nU8h5vWr8RCv.jpg"
            },
            "siteUrl": "https://anilist.co/staff/95290"
          }
        ]
      },
      {
        "role": "MAIN",
        "node": {
          "id": 4322,
          "name": {
            "first": "Ryouko",
            "last": "Hakubi",
            "native": "白眉魎呼",
            "alternative": [
              "Ryoko Orikasa"
            ]
          },
          "image": {
            "large": "https://s4.anilist.co/file/anilistcdn/character/large/4322.jpg",
            "medium": "https://s4.anilist.co/file/anilistcdn/character/medium/4322.jpg"
          },
          "siteUrl": "https://anilist.co/character/4322"
        },
        "voiceActors": [
          {
            "id": 95208,
            "name": {
              "first": "Ai",
              "last": "Orikasa",
              "native": "折笠愛"
            },
            "language": "JAPANESE",
            "image": {
              "large": "https://s4.anilist.co/file/anilistcdn/staff/large/n95208-DIfpWvWN401M.png",
              "medium": "https://s4.anilist.co/file/anilistcdn/staff/medium/n95208-DIfpWvWN401M.png"
            },
            "siteUrl": "https://anilist.co/staff/95208"
          }
        ]
      },
      {
        "role": "SUPPORTING",
        "node": {
          "id": 19114,
          "name": {
            "first": "Azaka",
            "last": null,
            "native": "阿座化",
            "alternative": []
          },
          "image": {
            "large": "https://s4.anilist.co/file/anilistcdn/character/large/b19114-Cc8MfeiQogeJ.png",
            "medium": "https://s4.anilist.co/file/anilistcdn/character/medium/b19114-Cc8MfeiQogeJ.png"
          },
          "siteUrl": "https://anilist.co/character/19114"
        },
        "voiceActors": [
          {
            "id": 95481,
            "name": {
              "first": "Kenichi",
              "last": "Ogata",
              "native": "緒方賢一"
            },
            "language": "JAPANESE",
            "image": {
              "large": "https://s4.anilist.co/file/anilistcdn/staff/large/n95481-1dPQbwMpvjul.png",
              "medium": "https://s4.anilist.co/file/anilistcdn/staff/medium/n95481-1dPQbwMpvjul.png"
            },
            "siteUrl": "https://anilist.co/staff/95481"
          }
        ]
      },
      {
        "role": "MAIN",
        "node": {
          "id": 5607,
          "name": {
            "first": "Mihoshi",
            "last": "Kuramitsu",
            "native": "九羅密美星",
            "alternative": []
          },
          "image": {
            "large": "https://s4.anilist.co/file/anilistcdn/character/large/5607.jpg",
            "medium": "https://s4.anilist.co/file/anilistcdn/character/medium/5607.jpg"
          },
          "siteUrl": "https://anilist.co/character/5607"
        },
        "voiceActors": [
          {
            "id": 95485,
            "name": {
              "first": "Yuuko",
              "last": "Mizutani",
              "native": "水谷優子"
            },
            "language": "JAPANESE",
            "image": {
              "large": "https://s4.anilist.co/file/anilistcdn/staff/large/n95485-fKXiqJdcVHHs.png",
              "medium": "https://s4.anilist.co/file/anilistcdn/staff/medium/n95485-fKXiqJdcVHHs.png"
            },
            "siteUrl": "https://anilist.co/staff/95485"
          }
        ]
      },
      {
        "role": "MAIN",
        "node": {
          "id": 274,
          "name": {
            "first": "Tenchi",
            "last": "Masaki",
            "native": "柾木天地",
            "alternative": []
          },
          "image": {
            "large": "https://s4.anilist.co/file/anilistcdn/character/large/b274-gPWMjIj0wULI.png",
            "medium": "https://s4.anilist.co/file/anilistcdn/character/medium/b274-gPWMjIj0wULI.png"
          },
          "siteUrl": "https://anilist.co/character/274"
        },
        "voiceActors": [
          {
            "id": 95488,
            "name": {
              "first": "Masami",
              "last": "Kikuchi",
              "native": "菊池正美"
            },
            "language": "JAPANESE",
            "image": {
              "large": "https://s4.anilist.co/file/anilistcdn/staff/large/n95488-XPg4VA6rW4jJ.png",
              "medium": "https://s4.anilist.co/file/anilistcdn/staff/medium/n95488-XPg4VA6rW4jJ.png"
            },
            "siteUrl": "https://anilist.co/staff/95488"
          }
        ]
      },
      {
        "role": "SUPPORTING",
        "node": {
          "id": 6667,
          "name": {
            "first": "Ryououki",
            "last": null,
            "native": "魎皇鬼",
            "alternative": [
              "Ryo-Ohki"
            ]
          },
          "image": {
            "large": "https://s4.anilist.co/file/anilistcdn/character/large/6667.jpg",
            "medium": "https://s4.anilist.co/file/anilistcdn/character/medium/6667.jpg"
          },
          "siteUrl": "https://anilist.co/character/6667"
        },
        "voiceActors": [
          {
            "id": 95782,
            "name": {
              "first": "Etsuko",
              "last": "Kozakura",
              "native": "小桜エツコ"
            },
            "language": "JAPANESE",
            "image": {
              "large": "https://s4.anilist.co/file/anilistcdn/staff/large/n95782-Zova2vUsykFw.png",
              "medium": "https://s4.anilist.co/file/anilistcdn/staff/medium/n95782-Zova2vUsykFw.png"
            },
            "siteUrl": "https://anilist.co/staff/95782"
          }
        ]
      },
      {
        "role": "MAIN",
        "node": {
          "id": 2404,
          "name": {
            "first": "Washu",
            "last": "Hakubi",
            "native": "白眉鷲羽",
            "alternative": [
              "Washu Kobayashi",
              "Washu Fitzgerald Kobayashi"
            ]
          },
          "image": {
            "large": "https://s4.anilist.co/file/anilistcdn/character/large/2404.jpg",
            "medium": "https://s4.anilist.co/file/anilistcdn/character/medium/2404.jpg"
          },
          "siteUrl": "https://anilist.co/character/2404"
        },
        "voiceActors": [
          {
            "id": 95983,
            "name": {
              "first": "Yuuko",
              "last": "Kobayashi",
              "native": "小林優子"
            },
            "language": "JAPANESE",
            "image": {
              "large": "https://s4.anilist.co/file/anilistcdn/staff/large/n95983-lqRFYTojbkRi.png",
              "medium": "https://s4.anilist.co/file/anilistcdn/staff/medium/n95983-lqRFYTojbkRi.png"
            },
            "siteUrl": "https://anilist.co/staff/95983"
          }
        ]
      },
      {
        "role": "SUPPORTING",
        "node": {
          "id": 15981,
          "name": {
            "first": "Mitsuki",
            "last": null,
            "native": "満奇",
            "alternative": []
          },
          "image": {
            "large": "https://s4.anilist.co/file/anilistcdn/character/large/15981.jpg",
            "medium": "https://s4.anilist.co/file/anilistcdn/character/medium/15981.jpg"
          },
          "siteUrl": "https://anilist.co/character/15981"
        },
        "voiceActors": [
          {
            "id": 96750,
            "name": {
              "first": "Yuka",
              "last": "Koyama",
              "native": "小山裕香"
            },
            "language": "JAPANESE",
            "image": {
              "large": "https://s4.anilist.co/file/anilistcdn/staff/large/96750-zfFmGKyKohpZ.jpg",
              "medium": "https://s4.anilist.co/file/anilistcdn/staff/medium/96750-zfFmGKyKohpZ.jpg"
            },
            "siteUrl": "https://anilist.co/staff/96750"
          }
        ]
      },
      {
        "role": "MAIN",
        "node": {
          "id": 5724,
          "name": {
            "first": "Ayeka",
            "last": "Masaki Jurai",
            "native": "柾木阿重霞樹雷",
            "alternative": []
          },
          "image": {
            "large": "https://s4.anilist.co/file/anilistcdn/character/large/5724.jpg",
            "medium": "https://s4.anilist.co/file/anilistcdn/character/medium/5724.jpg"
          },
          "siteUrl": "https://anilist.co/character/5724"
        },
        "voiceActors": [
          {
            "id": 95984,
            "name": {
              "first": "Yumi",
              "last": "Takada",
              "native": "高田由美"
            },
            "language": "JAPANESE",
            "image": {
              "large": "https://s4.anilist.co/file/anilistcdn/staff/large/n95984-CH3CaTnNBoQv.jpg",
              "medium": "https://s4.anilist.co/file/anilistcdn/staff/medium/n95984-CH3CaTnNBoQv.jpg"
            },
            "siteUrl": "https://anilist.co/staff/95984"
          }
        ]
      },
      {
        "role": "SUPPORTING",
        "node": {
          "id": 15704,
          "name": {
            "first": "Nagi",
            "last": null,
            "native": "那岐",
            "alternative": []
          },
          "image": {
            "large": "https://s4.anilist.co/file/anilistcdn/character/large/15704.jpg",
            "medium": "https://s4.anilist.co/file/anilistcdn/character/medium/15704.jpg"
          },
          "siteUrl": "https://anilist.co/character/15704"
        },
        "voiceActors": [
          {
            "id": 101397,
            "name": {
              "first": "Mizue",
              "last": "Ootsuka",
              "native": "大塚みずえ"
            },
            "language": "JAPANESE",
            "image": {
              "large": "https://s4.anilist.co/file/anilistcdn/staff/large/6397.jpg",
              "medium": "https://s4.anilist.co/file/anilistcdn/staff/medium/6397.jpg"
            },
            "siteUrl": "https://anilist.co/staff/101397"
          }
        ]
      },
      {
        "role": "SUPPORTING",
        "node": {
          "id": 82877,
          "name": {
            "first": "Youshou",
            "last": null,
            "native": "遙照",
            "alternative": []
          },
          "image": {
            "large": "https://s4.anilist.co/file/anilistcdn/character/large/82877.jpg",
            "medium": "https://s4.anilist.co/file/anilistcdn/character/medium/82877.jpg"
          },
          "siteUrl": "https://anilist.co/character/82877"
        },
        "voiceActors": [
          {
            "id": 95160,
            "name": {
              "first": "Takehito",
              "last": "Koyasu",
              "native": "子安武人"
            },
            "language": "JAPANESE",
            "image": {
              "large": "https://s4.anilist.co/file/anilistcdn/staff/large/n95160-jWevcH7BmfE1.jpg",
              "medium": "https://s4.anilist.co/file/anilistcdn/staff/medium/n95160-jWevcH7BmfE1.jpg"
            },
            "siteUrl": "https://anilist.co/staff/95160"
          }
        ]
      }
    ]
  },
  "staff": {
    "edges": [
      {
        "role": "Script (eps. 4, 9, 17, 21)",
        "node": {
          "id": 97471,
          "name": {
            "first": "Yousuke",
            "last": "Kuroda",
            "native": "黒田洋介"
          },
          "language": "JAPANESE",
          "image": {
            "large": "https://s4.anilist.co/file/anilistcdn/staff/large/n97471-QakOe67tAErz.png",
            "medium": "https://s4.anilist.co/file/anilistcdn/staff/medium/n97471-QakOe67tAErz.png"
          },
          "description": "Yousuke Kuroda is a Japanese screenwriter. He is affiliated with Studio Orphee and serves as the inside director (board of directors member).\n\nKuroda is a prolific writer in the anime industry. Having authored and scripted numerous anime series. Including several original productions. Some of the most notable are Infinite Ryvius, Scryed, Please☆Teacher!, Mobile Suit Gundam 00, and Waiting in the Summer.\n\nIn 2003, he won the Individual Award at the 8th Animation Kobe event.",
          "siteUrl": "https://anilist.co/staff/97471"
        }
      },
      {
        "role": "Episode Director",
        "node": {
          "id": 100055,
          "name": {
            "first": "Tatsuya",
            "last": "Ishihara",
            "native": "石原立也"
          },
          "language": "JAPANESE",
          "image": {
            "large": "https://s4.anilist.co/file/anilistcdn/staff/large/n100055-nZQ0hBIYNwW0.png",
            "medium": "https://s4.anilist.co/file/anilistcdn/staff/medium/n100055-nZQ0hBIYNwW0.png"
          },
          "description": "A prominent director and a key member of [Kyoto Animation](https://anilist.co/studio/2/).\n\nAfter graduating from Osaka Designers' College in the late '80s, Ishihara joined Kyoto Animation and began his career as an animator. In 1991, he made his debut as a director with [Shiawasette Naani](https://anilist.co/anime/13441/). After that, he switched his focus to directing. Back then Kyoto Animation was still a sub-contracting studio, so therefore Ishihara could only get a handful of opportunities directing. Some of the shows in which Ishihara got to direct multiple episodes were [Tenchi Muyou!](https://anilist.co/anime/696/), [Aka-chan to Boku](https://anilist.co/anime/1485/), [Hyper Police](https://anilist.co/anime/1180/), and [Inuyasha](https://anilist.co/anime/249/). He also storyboarded the majority of the episodes he directed.\n\nIn 2003, Kyoto Animation started their transformation into a full-fledged animation studio producing their first anime series, [Fullmetal Panic? Fumoffu](https://anilist.co/anime/72/). Ishihara directed and storyboarded the 7th episode of the show. Two years later in 2005, he made his proper directorial debut directing the studio's second TV show, [Air](https://anilist.co/anime/101/). The following year he directed the award winning anime series, [The Melancholy of Haruhi Suzumiya](https://anilist.co/anime/849/). From here Ishihara has gone on to direct multiple of Kyoto Animation's acclaimed works.",
          "siteUrl": "https://anilist.co/staff/100055"
        }
      },
      {
        "role": "Executive Producer (English)",
        "node": {
          "id": 100316,
          "name": {
            "first": "Gen",
            "last": "Fukunaga",
            "native": "福永元"
          },
          "language": "ENGLISH",
          "image": {
            "large": "https://s4.anilist.co/file/anilistcdn/staff/large/n100316-tG6FdGzqgxli.png",
            "medium": "https://s4.anilist.co/file/anilistcdn/staff/medium/n100316-tG6FdGzqgxli.png"
          },
          "description": "The founder and former representative director of [Funimation](https://anilist.co/studio/102/).\n\n**Non-anime roles:**\n- Policeman in \"Chuck E. Cheese in the Galaxy 5000\"",
          "siteUrl": "https://anilist.co/staff/100316"
        }
      },
      {
        "role": "Storyboard  (eps 10, 16, 22)",
        "node": {
          "id": 100640,
          "name": {
            "first": "Akitarou",
            "last": "Daichi",
            "native": "大地丙太郎"
          },
          "language": "JAPANESE",
          "image": {
            "large": "https://s4.anilist.co/file/anilistcdn/staff/large/n100640-SjBjtVLwC5gz.png",
            "medium": "https://s4.anilist.co/file/anilistcdn/staff/medium/n100640-SjBjtVLwC5gz.png"
          },
          "description": "[Twitter](https://twitter.com/akitaroh_le) | [Website](http://www5c.biglobe.ne.jp/~akitaroh/) | [Wiki (jp)](https://ja.wikipedia.org/wiki/大地丙太郎)\n\nHe is a Tokyo Polytechnic University graduate. Although Daichi was an aspiring stage photographer he instead joined animation photography company Tokyo Animation Film where he continued to work for 5 years, although he temporarily changed jobs and shot live-action karaoke videos instead. In 1991 he left his employer, worked at a game production for half a year, and returned to the animation industry where he would study under animation director [Tetsuo Yasumi](https://anilist.co/staff/111207/). Daichi would advance into episode direction and caught the eyes of [Tatsuo Satou](https://anilist.co/staff/100391/) and [Hiroaki Sakurai](https://anilist.co/staff/101153/) who were impressed with his work on [*Akazukin Chacha*](https://anilist.co/anime/103/Akazukin-Chacha). Daichi made his solo directorial debut in 1995 with [*Nurse Angel Ririka SOS*](https://anilist.co/anime/616/Nurse-Angel-Ririka-SOS). Since 2015 he serves as scriptwriter and director for [*Kodomo no Omocha*](https://anilist.co/anime/1486/Kodomo-no-Omocha/)'s stage version of which he directed the anime as well. Presently he's a freelance director.\n\n**Style**\nHe specializes in high-tension comedy and often includes comedy and lighthearted moments even in more serious works. In his comedies he often smoothly deforms the characters far beyond their design, inspired by gag manga king [Fujio Akatsuka](https://anilist.co/staff/97141/). His directing work tends to include live-action images or brief flashbacks from past episodes. Since childhood Daichi became affected and inspired by the works of famous jidaigeki actor *Joushirou Konoe* inspiring him to make more historical samurai works.\n\nDaichi is particular about choosing voice actors and has discovered several talents such as [Ayaka Saitou](https://anilist.co/staff/95222/), [Nozomi Sasaki](https://anilist.co/staff/95580/), and [Reiko Yasuhara](https://anilist.co/staff/95373/). \n\n**Accolades**\n- [*Ojarumaru*](https://anilist.co/anime/4459/Ojarumaru) won the 1999 Japan Media Arts Festival Animation Excellence Award.\n- [*Maksete Iruka!*](https://anilist.co/anime/2791/Makasete-Iruka/) won the 2004 Japan Media Arts Festival Animation Excellence Award.\n- [*Gyagu Manga Biyori*](https://anilist.co/anime/1196/Gyagu-Manga-Biyori) was recommended by the Japan Media Arts Festival Animation committee in 2005.\n\n**Controversies**\nIn 2018 and 2019 voice actress [Hiroko Konishi](https://anilist.co/staff/96545/Hiroko-Konishi) alleged that she was propositioned by her manager to enter a mixed bath with Daichi in the nude and was blacklisted from the voice acting industry when she refused.",
          "siteUrl": "https://anilist.co/staff/100640"
        }
      },
      {
        "role": "Script (ep 19)",
        "node": {
          "id": 101077,
          "name": {
            "first": "Mayori",
            "last": "Sekijima",
            "native": "関島眞頼"
          },
          "language": "JAPANESE",
          "image": {
            "large": "https://s4.anilist.co/file/anilistcdn/staff/large/n101077-DUqucMJaiUZb.png",
            "medium": "https://s4.anilist.co/file/anilistcdn/staff/medium/n101077-DUqucMJaiUZb.png"
          },
          "description": "[Wiki (jp)](https://ja.wikipedia.org/wiki/関島眞頼)",
          "siteUrl": "https://anilist.co/staff/101077"
        }
      },
      {
        "role": "Storyboard  (eps 20, 25)",
        "node": {
          "id": 101180,
          "name": {
            "first": "Yoshiaki",
            "last": "Iwasaki",
            "native": "岩崎良明"
          },
          "language": "JAPANESE",
          "image": {
            "large": "https://s4.anilist.co/file/anilistcdn/staff/large/6180.jpg",
            "medium": "https://s4.anilist.co/file/anilistcdn/staff/medium/6180.jpg"
          },
          "description": null,
          "siteUrl": "https://anilist.co/staff/101180"
        }
      },
      {
        "role": "Episode Director  (1, 6, 12, 20, 25)",
        "node": {
          "id": 101180,
          "name": {
            "first": "Yoshiaki",
            "last": "Iwasaki",
            "native": "岩崎良明"
          },
          "language": "JAPANESE",
          "image": {
            "large": "https://s4.anilist.co/file/anilistcdn/staff/large/6180.jpg",
            "medium": "https://s4.anilist.co/file/anilistcdn/staff/medium/6180.jpg"
          },
          "description": null,
          "siteUrl": "https://anilist.co/staff/101180"
        }
      },
      {
        "role": "Director",
        "node": {
          "id": 101228,
          "name": {
            "first": "Hiroshi",
            "last": "Negishi",
            "native": "ねぎしひろし"
          },
          "language": "JAPANESE",
          "image": {
            "large": "https://s4.anilist.co/file/anilistcdn/staff/large/6228.jpg",
            "medium": "https://s4.anilist.co/file/anilistcdn/staff/medium/6228.jpg"
          },
          "description": "[Wiki (jp)](https://ja.wikipedia.org/wiki/%E3%81%AD%E3%81%8E%E3%81%97%E3%81%B2%E3%82%8D%E3%81%97)\n\nHiroshi Negishi is a director, screenwriter and storyboard artist.",
          "siteUrl": "https://anilist.co/staff/101228"
        }
      },
      {
        "role": "Key Animation  (ED 3)",
        "node": {
          "id": 101403,
          "name": {
            "first": "Takahiro",
            "last": "Kishida",
            "native": "岸田隆宏"
          },
          "language": "JAPANESE",
          "image": {
            "large": "https://s4.anilist.co/file/anilistcdn/staff/large/n101403-nSqMj1CdIn1e.png",
            "medium": "https://s4.anilist.co/file/anilistcdn/staff/medium/n101403-nSqMj1CdIn1e.png"
          },
          "description": "[Wiki (jp)](https://ja.wikipedia.org/wiki/%E5%B2%B8%E7%94%B0%E9%9A%86%E5%AE%8F)\n\nTakahiro Kishida is an animator and renown character designer.\n\nKishida's designs are well received by animators and attract talent into shows easily. He is also praised for his shot composition skills and copies of his layouts are widely distributed in the industry as drawing reference. Nowadays he is mostly only credited for character design in the shows he participates in, but in reality he works as an animation director uncredited quite often. He rarely heavily corrects the key animator's cuts, strongly believing that the animators' distinctiveness should be noticeable.\n\nNoted for his designs on shows like [Haikyuu](https://anilist.co/anime/20464/), [Serial Experiments Lain](https://anilist.co/anime/339/), [Madoka Magica](https://anilist.co/anime/9756/), [Baccano](https://anilist.co/anime/2251/) and more.",
          "siteUrl": "https://anilist.co/staff/101403"
        }
      },
      {
        "role": "Key Animation",
        "node": {
          "id": 101727,
          "name": {
            "first": "Takahiro",
            "last": "Kagami",
            "native": "加々美高浩"
          },
          "language": "JAPANESE",
          "image": {
            "large": "https://s4.anilist.co/file/anilistcdn/staff/large/n101727-BscMKGNhO7Di.jpg",
            "medium": "https://s4.anilist.co/file/anilistcdn/staff/medium/n101727-BscMKGNhO7Di.jpg"
          },
          "description": "[Twitter](https://twitter.com/jetikariya50)\n\nAcknowledged internationally for his work on [Yu☆Gi☆Oh!](https://anilist.co/anime/481/) and [Death Note](https://anilist.co/anime/1535/).\n\nFamous for his depictions of fingers and the \"Joey Chin\" in Yu-Gi-Oh!.",
          "siteUrl": "https://anilist.co/staff/101727"
        }
      },
      {
        "role": "In-Between Animation  (ep 12)",
        "node": {
          "id": 101738,
          "name": {
            "first": "Takeo",
            "last": "Takahashi",
            "native": "高橋丈夫"
          },
          "language": "JAPANESE",
          "image": {
            "large": "https://s4.anilist.co/file/anilistcdn/staff/large/n101738-1XlVpj72X1xy.png",
            "medium": "https://s4.anilist.co/file/anilistcdn/staff/medium/n101738-1XlVpj72X1xy.png"
          },
          "description": "Originally an animator. Often works with [Hijiri Sanpei](https://anilist.co/staff/149565/).",
          "siteUrl": "https://anilist.co/staff/101738"
        }
      },
      {
        "role": "Animation Director  (ep 4, 11)",
        "node": {
          "id": 101936,
          "name": {
            "first": "Yukari",
            "last": "Kobayashi",
            "native": "小林ゆかり"
          },
          "language": "JAPANESE",
          "image": {
            "large": "https://s4.anilist.co/file/anilistcdn/staff/large/n101936-Q7x8GkJtXFRo.png",
            "medium": "https://s4.anilist.co/file/anilistcdn/staff/medium/n101936-Q7x8GkJtXFRo.png"
          },
          "description": null,
          "siteUrl": "https://anilist.co/staff/101936"
        }
      },
      {
        "role": "Key Animation  (ep 12, 25)",
        "node": {
          "id": 102190,
          "name": {
            "first": "Manabu",
            "last": "Ono",
            "native": "小野学"
          },
          "language": "JAPANESE",
          "image": {
            "large": "https://s4.anilist.co/file/anilistcdn/staff/large/n102190-UZFWw4KLbXF2.png",
            "medium": "https://s4.anilist.co/file/anilistcdn/staff/medium/n102190-UZFWw4KLbXF2.png"
          },
          "description": "[Twitter](https://twitter.com/gaku3900) | [Wiki (jp)](https://ja.wikipedia.org/wiki/小野学_(アニメーション監督%29)",
          "siteUrl": "https://anilist.co/staff/102190"
        }
      },
      {
        "role": "Key Animation  (ep 2, 7, 9, 14-15, 21, 24)",
        "node": {
          "id": 102679,
          "name": {
            "first": "Noboru",
            "last": "Koizumi",
            "native": "小泉昇"
          },
          "language": "JAPANESE",
          "image": {
            "large": "https://s4.anilist.co/file/anilistcdn/staff/large/n102679-vtVFFvIUzvsy.png",
            "medium": "https://s4.anilist.co/file/anilistcdn/staff/medium/n102679-vtVFFvIUzvsy.png"
          },
          "description": "A Japanese animator, character designer, animation supervisor and animation director. He is widely known for his range of character designs for the one piece seasons 1-11.",
          "siteUrl": "https://anilist.co/staff/102679"
        }
      },
      {
        "role": "In-Between Animation  (ep 2)",
        "node": {
          "id": 103057,
          "name": {
            "first": "Masaki",
            "last": "Yamada",
            "native": "山田正樹"
          },
          "language": "JAPANESE",
          "image": {
            "large": "https://s4.anilist.co/file/anilistcdn/staff/large/8057.jpg",
            "medium": "https://s4.anilist.co/file/anilistcdn/staff/medium/8057.jpg"
          },
          "description": null,
          "siteUrl": "https://anilist.co/staff/103057"
        }
      },
      {
        "role": "Key Animation  (eps 20, 25)",
        "node": {
          "id": 103099,
          "name": {
            "first": "Naoyuki",
            "last": "Konno",
            "native": "紺野直幸"
          },
          "language": "JAPANESE",
          "image": {
            "large": "https://s4.anilist.co/file/anilistcdn/staff/large/8099.jpg",
            "medium": "https://s4.anilist.co/file/anilistcdn/staff/medium/8099.jpg"
          },
          "description": "[Sakugabooru](https://www.sakugabooru.com/post?tags=naoyuki_konno)\n\n__Naoyuki Konno__ is a Japanese animator and director. He is particularly known for his work on several adaptations of [Shoutarou Ishinomori's](https://anilist.co/staff/97478/Shoutarou-Ishinomori) works as well as his animation style, being renowned as one of the Kanada-school animators.",
          "siteUrl": "https://anilist.co/staff/103099"
        }
      },
      {
        "role": "In-Between Animation  (ep 5)",
        "node": {
          "id": 103835,
          "name": {
            "first": "Yoshihiro",
            "last": "Watanabe",
            "native": "渡邊義弘"
          },
          "language": "JAPANESE",
          "image": {
            "large": "https://s4.anilist.co/file/anilistcdn/staff/large/n103835-cox4ljwK9VO2.png",
            "medium": "https://s4.anilist.co/file/anilistcdn/staff/medium/n103835-cox4ljwK9VO2.png"
          },
          "description": "[Twitter](https://twitter.com/xexex36) | [Instagram](https://www.instagram.com/yoshihiro_watanabe1971/) | [Wiki (jp)](https://ja.wikipedia.org/wiki/渡邊義弘_(アニメーター%29)\n\nAn animator, character designer and adult game artist.\n\n_Not to be confused with the producer [of the same name.](https://anilist.co/staff/233840)_",
          "siteUrl": "https://anilist.co/staff/103835"
        }
      },
      {
        "role": "Animation Director  (eps. 3, 8, 13, 18, 23)",
        "node": {
          "id": 152241,
          "name": {
            "first": "Takeshi",
            "last": "Kusaka",
            "native": "日下岳史"
          },
          "language": "JAPANESE",
          "image": {
            "large": "https://s4.anilist.co/file/anilistcdn/staff/large/default.jpg",
            "medium": "https://s4.anilist.co/file/anilistcdn/staff/medium/default.jpg"
          },
          "description": null,
          "siteUrl": "https://anilist.co/staff/152241"
        }
      },
      {
        "role": "Key Animation  (ep. 8, 18)",
        "node": {
          "id": 152241,
          "name": {
            "first": "Takeshi",
            "last": "Kusaka",
            "native": "日下岳史"
          },
          "language": "JAPANESE",
          "image": {
            "large": "https://s4.anilist.co/file/anilistcdn/staff/large/default.jpg",
            "medium": "https://s4.anilist.co/file/anilistcdn/staff/medium/default.jpg"
          },
          "description": null,
          "siteUrl": "https://anilist.co/staff/152241"
        }
      },
      {
        "role": "Animation Director",
        "node": {
          "id": 105142,
          "name": {
            "first": "Masaki",
            "last": "Tanaka",
            "native": "田中誠輝"
          },
          "language": "JAPANESE",
          "image": {
            "large": "https://s4.anilist.co/file/anilistcdn/staff/large/default.jpg",
            "medium": "https://s4.anilist.co/file/anilistcdn/staff/medium/default.jpg"
          },
          "description": null,
          "siteUrl": "https://anilist.co/staff/105142"
        }
      },
      {
        "role": "Planning",
        "node": {
          "id": 105169,
          "name": {
            "first": "Tarou",
            "last": "Maki",
            "native": "真木太郎"
          },
          "language": "JAPANESE",
          "image": {
            "large": "https://s4.anilist.co/file/anilistcdn/staff/large/n105169-B4nIkRmO8wKR.png",
            "medium": "https://s4.anilist.co/file/anilistcdn/staff/medium/n105169-B4nIkRmO8wKR.png"
          },
          "description": "[Wiki (jp)](https://ja.wikipedia.org/wiki/真木太郎)\n\nTarou Maki is a producer. He graduated from the Department of Law at Waseda University in 1977 and joined Pioneer. In 1997 he founded production studio [Genco](https://anilist.co/studio/79/) and serves today still as its president.",
          "siteUrl": "https://anilist.co/staff/105169"
        }
      },
      {
        "role": "In-Between Animation",
        "node": {
          "id": 105285,
          "name": {
            "first": "Satoshi",
            "last": "Nishimura",
            "native": "西村聡"
          },
          "language": "JAPANESE",
          "image": {
            "large": "https://s4.anilist.co/file/anilistcdn/staff/large/n105285-JDe0Ndf0YPlj.jpg",
            "medium": "https://s4.anilist.co/file/anilistcdn/staff/medium/n105285-JDe0Ndf0YPlj.jpg"
          },
          "description": null,
          "siteUrl": "https://anilist.co/staff/105285"
        }
      },
      {
        "role": "Key Animation  (eps 18, 23)",
        "node": {
          "id": 106799,
          "name": {
            "first": "Mayumi",
            "last": "Watanabe",
            "native": "渡辺真由美"
          },
          "language": "JAPANESE",
          "image": {
            "large": "https://s4.anilist.co/file/anilistcdn/staff/large/n106799-r9c2A0DJHWWj.jpg",
            "medium": "https://s4.anilist.co/file/anilistcdn/staff/medium/n106799-r9c2A0DJHWWj.jpg"
          },
          "description": "[Twitter](https://twitter.com/watawayuwaasa)\n\nOriginating from [Kaname Production](https://anilist.co/studio/288/).\n\nMarried to producer [Saburou Oomiya](https://anilist.co/staff/114329/).",
          "siteUrl": "https://anilist.co/staff/106799"
        }
      },
      {
        "role": "Key Animation  (eps 5, 10)",
        "node": {
          "id": 108709,
          "name": {
            "first": "Nobuyuki",
            "last": "Takeuchi",
            "native": "武内宣之"
          },
          "language": "JAPANESE",
          "image": {
            "large": "https://s4.anilist.co/file/anilistcdn/staff/large/n108709-9x28xKtoBKx1.png",
            "medium": "https://s4.anilist.co/file/anilistcdn/staff/medium/n108709-9x28xKtoBKx1.png"
          },
          "description": "[Twitter](https://twitter.com/i/user/1134744619810344960)\n\nOriginating from Dragon Production.",
          "siteUrl": "https://anilist.co/staff/108709"
        }
      },
      {
        "role": "Music",
        "node": {
          "id": 109739,
          "name": {
            "first": "Seikou",
            "last": "Nagaoka",
            "native": "長岡成貢"
          },
          "language": "JAPANESE",
          "image": {
            "large": "https://s4.anilist.co/file/anilistcdn/staff/large/n109739-Avb632kGZ4hh.png",
            "medium": "https://s4.anilist.co/file/anilistcdn/staff/medium/n109739-Avb632kGZ4hh.png"
          },
          "description": "[Twitter](https://twitter.com/sei_kou) | [Website](https://www.himemiko.co/) | [Wiki (jp)](https://ja.wikipedia.org/wiki/長岡成貢)\n\nA self-taught composer and arranger.",
          "siteUrl": "https://anilist.co/staff/109739"
        }
      }
    ]
  },
  "studios": {
    "edges": [
      {
        "isMain": true,
        "node": {
          "id": 48,
          "name": "AIC",
          "siteUrl": "https://anilist.co/studio/48"
        }
      },
      {
        "isMain": false,
        "node": {
          "id": 102,
          "name": "Funimation",
          "siteUrl": "https://anilist.co/studio/102"
        }
      },
      {
        "isMain": false,
        "node": {
          "id": 204,
          "name": "Pioneer LDC",
          "siteUrl": "https://anilist.co/studio/204"
        }
      },
      {
        "isMain": false,
        "node": {
          "id": 479,
          "name": "DOGA Productions",
          "siteUrl": "https://anilist.co/studio/479"
        }
      },
      {
        "isMain": false,
        "node": {
          "id": 2,
          "name": "Kyoto Animation",
          "siteUrl": "https://anilist.co/studio/2"
        }
      },
      {
        "isMain": false,
        "node": {
          "id": 207,
          "name": "Magic Bus",
          "siteUrl": "https://anilist.co/studio/207"
        }
      }
    ]
  },
  "isAdult": false,
  "airingSchedule": {
    "edges": []
  },
  "externalLinks": [],
  "streamingEpisodes": [
    {
      "title": "Episode 1 - No Need for Discussions!",
      "thumbnail": "https://img1.ak.crunchyroll.com/i/spire4-tmb/fcf36e61c31c506cc4200fe7044301fb1514059345_full.jpg",
      "url": "http://www.crunchyroll.com/tenchi-muyo-tenchi-universe/episode-1-no-need-for-discussions-757497",
      "site": "Crunchyroll"
    },
    {
      "title": "Episode 2 - No Need for Princesses!",
      "thumbnail": "https://img1.ak.crunchyroll.com/i/spire4-tmb/4bfda3c68bb70c2779f9b3eac8af7a6d1514059656_full.jpg",
      "url": "http://www.crunchyroll.com/tenchi-muyo-tenchi-universe/episode-2-no-need-for-princesses-757499",
      "site": "Crunchyroll"
    },
    {
      "title": "Episode 3 - No Need for Worries!",
      "thumbnail": "https://img1.ak.crunchyroll.com/i/spire2-tmb/8499cbedfe02a49347d44758729f580f1514060058_full.jpg",
      "url": "http://www.crunchyroll.com/tenchi-muyo-tenchi-universe/episode-3-no-need-for-worries-757503",
      "site": "Crunchyroll"
    },
    {
      "title": "Episode 4 - No Need for Monsters!",
      "thumbnail": "https://img1.ak.crunchyroll.com/i/spire3-tmb/c817969bc15f74865f4e84312641484f1514060420_full.jpg",
      "url": "http://www.crunchyroll.com/tenchi-muyo-tenchi-universe/episode-4-no-need-for-monsters-757507",
      "site": "Crunchyroll"
    },
    {
      "title": "Episode 5 - No Need for Partners!",
      "thumbnail": "https://img1.ak.crunchyroll.com/i/spire3-tmb/82a4156b87ac8fbaab3ce2d19ba7922f1514061005_full.jpg",
      "url": "http://www.crunchyroll.com/tenchi-muyo-tenchi-universe/episode-5-no-need-for-partners-757511",
      "site": "Crunchyroll"
    },
    {
      "title": "Episode 6 - No Need for Resident Officers!",
      "thumbnail": "https://img1.ak.crunchyroll.com/i/spire2-tmb/ad62fd10505fc56f900f50f6f1e421c61514061345_full.jpg",
      "url": "http://www.crunchyroll.com/tenchi-muyo-tenchi-universe/episode-6-no-need-for-resident-officers-757515",
      "site": "Crunchyroll"
    },
    {
      "title": "Episode 7 - No Need for Carnivals!",
      "thumbnail": "https://img1.ak.crunchyroll.com/i/spire1-tmb/8a9f08abed73ff84d9ee15bd9758d9c71514061637_full.jpg",
      "url": "http://www.crunchyroll.com/tenchi-muyo-tenchi-universe/episode-7-no-need-for-carnivals-757519",
      "site": "Crunchyroll"
    },
    {
      "title": "Episode 8 - No Need for a Genius!",
      "thumbnail": "https://img1.ak.crunchyroll.com/i/spire4-tmb/96c8967a196083b78159720ecc98ffbb1514061880_full.jpg",
      "url": "http://www.crunchyroll.com/tenchi-muyo-tenchi-universe/episode-8-no-need-for-a-genius-757525",
      "site": "Crunchyroll"
    },
    {
      "title": "Episode 9 - No Need for Memories!",
      "thumbnail": "https://img1.ak.crunchyroll.com/i/spire4-tmb/1d422cf04714534cc8df9dd8e5d220c61514062267_full.jpg",
      "url": "http://www.crunchyroll.com/tenchi-muyo-tenchi-universe/episode-9-no-need-for-memories-757529",
      "site": "Crunchyroll"
    },
    {
      "title": "Episode 10 - No Need for an Arch Rival!",
      "thumbnail": "https://img1.ak.crunchyroll.com/i/spire4-tmb/09a43a9e8ca0f308c9fad23b95bd09b11514069494_full.jpg",
      "url": "http://www.crunchyroll.com/tenchi-muyo-tenchi-universe/episode-10-no-need-for-an-arch-rival-757535",
      "site": "Crunchyroll"
    },
    {
      "title": "Episode 11 - Time and Space Adventures Part I",
      "thumbnail": "https://img1.ak.crunchyroll.com/i/spire3-tmb/77952f2e52c5639f3a18ec21eeec44e61514069975_full.jpg",
      "url": "http://www.crunchyroll.com/tenchi-muyo-tenchi-universe/episode-11-time-and-space-adventures-part-i-757537",
      "site": "Crunchyroll"
    },
    {
      "title": "Episode 12 - Time and Space Adventures Part II",
      "thumbnail": "https://img1.ak.crunchyroll.com/i/spire4-tmb/26a2a8f90a60c5c46221ba5473069c421514070242_full.jpg",
      "url": "http://www.crunchyroll.com/tenchi-muyo-tenchi-universe/episode-12-time-and-space-adventures-part-ii-757541",
      "site": "Crunchyroll"
    },
    {
      "title": "Episode 13 - Time and Space Adventures Part III",
      "thumbnail": "https://img1.ak.crunchyroll.com/i/spire4-tmb/717b2b0c5092fc39dd998b3c9dbaa4371514070622_full.jpg",
      "url": "http://www.crunchyroll.com/tenchi-muyo-tenchi-universe/episode-13-time-and-space-adventures-part-iii-757545",
      "site": "Crunchyroll"
    },
    {
      "title": "Episode 14 - No Need for a Rebellion!",
      "thumbnail": "https://img1.ak.crunchyroll.com/i/spire2-tmb/913f05a78b0114766d8653b680e146001514071043_full.jpg",
      "url": "http://www.crunchyroll.com/tenchi-muyo-tenchi-universe/episode-14-no-need-for-a-rebellion-757549",
      "site": "Crunchyroll"
    },
    {
      "title": "Episode 15 - No Need for an Escape!",
      "thumbnail": "https://img1.ak.crunchyroll.com/i/spire2-tmb/abca2e38029545821402f941155766ec1514071512_full.jpg",
      "url": "http://www.crunchyroll.com/tenchi-muyo-tenchi-universe/episode-15-no-need-for-an-escape-757553",
      "site": "Crunchyroll"
    },
    {
      "title": "Episode 16 - No Need for Hiding",
      "thumbnail": "https://img1.ak.crunchyroll.com/i/spire2-tmb/48de7afb9e74ceeab6e1d0be4e9279511514071791_full.jpg",
      "url": "http://www.crunchyroll.com/tenchi-muyo-tenchi-universe/episode-16-no-need-for-hiding-757557",
      "site": "Crunchyroll"
    },
    {
      "title": "Episode 17 - No Need for Hunger",
      "thumbnail": "https://img1.ak.crunchyroll.com/i/spire2-tmb/82430b2b1ea371e9cf5e8a781c9cfd641514072072_full.jpg",
      "url": "http://www.crunchyroll.com/tenchi-muyo-tenchi-universe/episode-17-no-need-for-hunger-757561",
      "site": "Crunchyroll"
    },
    {
      "title": "Episode 18 - No Need for a Ghost",
      "thumbnail": "https://img1.ak.crunchyroll.com/i/spire1-tmb/3a33405f191a4f40327e374dc893fcde1514072457_full.jpg",
      "url": "http://www.crunchyroll.com/tenchi-muyo-tenchi-universe/episode-18-no-need-for-a-ghost-757565",
      "site": "Crunchyroll"
    },
    {
      "title": "Episode 19 - No Need for Runaways",
      "thumbnail": "https://img1.ak.crunchyroll.com/i/spire3-tmb/b8f83b98579a71412186fce382ae4fe91514072880_full.jpg",
      "url": "http://www.crunchyroll.com/tenchi-muyo-tenchi-universe/episode-19-no-need-for-runaways-757569",
      "site": "Crunchyroll"
    },
    {
      "title": "Episode 20 - No Need for Swimsuits",
      "thumbnail": "https://img1.ak.crunchyroll.com/i/spire4-tmb/2e635e593952e2289e51cd1b5713d7131514073371_full.jpg",
      "url": "http://www.crunchyroll.com/tenchi-muyo-tenchi-universe/episode-20-no-need-for-swimsuits-757573",
      "site": "Crunchyroll"
    },
    {
      "title": "Episode 21 - No Need for a Checkpoint",
      "thumbnail": "https://img1.ak.crunchyroll.com/i/spire3-tmb/81b91d8c389391177594ade3475ca0c41514073574_full.jpg",
      "url": "http://www.crunchyroll.com/tenchi-muyo-tenchi-universe/episode-21-no-need-for-a-checkpoint-757577",
      "site": "Crunchyroll"
    },
    {
      "title": "Episode 22 - No Need for Knights!",
      "thumbnail": "https://img1.ak.crunchyroll.com/i/spire4-tmb/8ce66d0478151607dbee8d3f64a6b6411514073930_full.jpg",
      "url": "http://www.crunchyroll.com/tenchi-muyo-tenchi-universe/episode-22-no-need-for-knights-757581",
      "site": "Crunchyroll"
    },
    {
      "title": "Episode 23 - No Need for Karma",
      "thumbnail": "https://img1.ak.crunchyroll.com/i/spire3-tmb/be2c944c2263addc1f5fc1ca299f537d1514074345_full.jpg",
      "url": "http://www.crunchyroll.com/tenchi-muyo-tenchi-universe/episode-23-no-need-for-karma-757585",
      "site": "Crunchyroll"
    },
    {
      "title": "Episode 24 - No Need for Ryoko",
      "thumbnail": "https://img1.ak.crunchyroll.com/i/spire3-tmb/cb53c6b54742de09d73c9cc14e45f75f1514074626_full.jpg",
      "url": "http://www.crunchyroll.com/tenchi-muyo-tenchi-universe/episode-24-no-need-for-ryoko-757589",
      "site": "Crunchyroll"
    },
    {
      "title": "Episode 25 - No Need for a Showdown!",
      "thumbnail": "https://img1.ak.crunchyroll.com/i/spire2-tmb/8c15f1e45d38028f683390485c99b6c21514075105_full.jpg",
      "url": "http://www.crunchyroll.com/tenchi-muyo-tenchi-universe/episode-25-no-need-for-a-showdown-757593",
      "site": "Crunchyroll"
    },
    {
      "title": "Episode 26 - No Need for a Conclusion",
      "thumbnail": "https://img1.ak.crunchyroll.com/i/spire4-tmb/948d8d6e8f85fec6ff17ed93ce4775da1514075354_full.jpg",
      "url": "http://www.crunchyroll.com/tenchi-muyo-tenchi-universe/episode-26-no-need-for-a-conclusion-757597",
      "site": "Crunchyroll"
    }
  ],
  "rankings": [
    {
      "id": 1283,
      "rank": 10,
      "type": "RATED",
      "format": "TV",
      "year": 1995,
      "season": null,
      "allTime": false,
      "context": "highest rated"
    },
    {
      "id": 1311,
      "rank": 6,
      "type": "POPULAR",
      "format": "TV",
      "year": 1995,
      "season": null,
      "allTime": false,
      "context": "most popular"
    }
  ],
  "recommendations": {
    "edges": [
      {
        "node": {
          "id": 29615,
          "rating": 4,
          "media": {
            "id": 696,
            "title": {
              "native": "天地無用！"
            }
          },
          "mediaRecommendation": {
            "id": 581,
            "title": {
              "native": "炎のらびりんす"
            }
          }
        }
      },
      {
        "node": {
          "id": 30956,
          "rating": 10,
          "media": {
            "id": 696,
            "title": {
              "native": "天地無用！"
            }
          },
          "mediaRecommendation": {
            "id": 573,
            "title": {
              "native": "セイバーマリオネットJ"
            }
          }
        }
      },
      {
        "node": {
          "id": 101919,
          "rating": 7,
          "media": {
            "id": 696,
            "title": {
              "native": "天地無用！"
            }
          },
          "mediaRecommendation": {
            "id": 992,
            "title": {
              "native": "デュアル！ぱられルンルン物語"
            }
          }
        }
      },
      {
        "node": {
          "id": 104549,
          "rating": 7,
          "media": {
            "id": 696,
            "title": {
              "native": "天地無用！"
            }
          },
          "mediaRecommendation": {
            "id": 180,
            "title": {
              "native": "ヴァンドレッド"
            }
          }
        }
      },
      {
        "node": {
          "id": 105208,
          "rating": 4,
          "media": {
            "id": 696,
            "title": {
              "native": "天地無用！"
            }
          },
          "mediaRecommendation": {
            "id": 538,
            "title": {
              "native": "新・天地無用!"
            }
          }
        }
      },
      {
        "node": {
          "id": 122860,
          "rating": 4,
          "media": {
            "id": 696,
            "title": {
              "native": "天地無用！"
            }
          },
          "mediaRecommendation": {
            "id": 189,
            "title": {
              "native": "ラブひな"
            }
          }
        }
      },
      {
        "node": {
          "id": 122862,
          "rating": 11,
          "media": {
            "id": 696,
            "title": {
              "native": "天地無用！"
            }
          },
          "mediaRecommendation": {
            "id": 218,
            "title": {
              "native": "機動戦艦ナデシコ"
            }
          }
        }
      },
      {
        "node": {
          "id": 143727,
          "rating": 2,
          "media": {
            "id": 696,
            "title": {
              "native": "天地無用！"
            }
          },
          "mediaRecommendation": {
            "id": 24,
            "title": {
              "native": "スクールランブル"
            }
          }
        }
      },
      {
        "node": {
          "id": 148754,
          "rating": 5,
          "media": {
            "id": 696,
            "title": {
              "native": "天地無用！"
            }
          },
          "mediaRecommendation": {
            "id": 50,
            "title": {
              "native": "ああっ女神さまっ (TV)"
            }
          }
        }
      },
      {
        "node": {
          "id": 151185,
          "rating": 1,
          "media": {
            "id": 696,
            "title": {
              "native": "天地無用！"
            }
          },
          "mediaRecommendation": {
            "id": 1232,
            "title": {
              "native": "セイバーマリオネットR"
            }
          }
        }
      },
      {
        "node": {
          "id": 159475,
          "rating": 2,
          "media": {
            "id": 696,
            "title": {
              "native": "天地無用！"
            }
          },
          "mediaRecommendation": {
            "id": 20638,
            "title": {
              "native": "六畳間の侵略者!?"
            }
          }
        }
      },
      {
        "node": {
          "id": 169838,
          "rating": 3,
          "media": {
            "id": 696,
            "title": {
              "native": "天地無用！"
            }
          },
          "mediaRecommendation": {
            "id": 400,
            "title": {
              "native": "星方武侠アウトロースター"
            }
          }
        }
      },
      {
        "node": {
          "id": 215773,
          "rating": 6,
          "media": {
            "id": 696,
            "title": {
              "native": "天地無用！"
            }
          },
          "mediaRecommendation": {
            "id": 383,
            "title": {
              "native": "ギャラクシーエンジェル"
            }
          }
        }
      },
      {
        "node": {
          "id": 218492,
          "rating": 4,
          "media": {
            "id": 696,
            "title": {
              "native": "天地無用！"
            }
          },
          "mediaRecommendation": {
            "id": 116,
            "title": {
              "native": "神秘の世界エルハザード (TV)"
            }
          }
        }
      },
      {
        "node": {
          "id": 218494,
          "rating": 2,
          "media": {
            "id": 696,
            "title": {
              "native": "天地無用！"
            }
          },
          "mediaRecommendation": {
            "id": 1186,
            "title": {
              "native": "バトルアスリーテス大運動会"
            }
          }
        }
      },
      {
        "node": {
          "id": 230881,
          "rating": 3,
          "media": {
            "id": 696,
            "title": {
              "native": "天地無用！"
            }
          },
          "mediaRecommendation": {
            "id": 563,
            "title": {
              "native": "Ｄ・Ｎ・Ａ² ～何処かで失くしたあいつのアイツ～"
            }
          }
        }
      },
      {
        "node": {
          "id": 316654,
          "rating": 1,
          "media": {
            "id": 696,
            "title": {
              "native": "天地無用！"
            }
          },
          "mediaRecommendation": {
            "id": 1823,
            "title": {
              "native": "神八剣伝"
            }
          }
        }
      },
      {
        "node": {
          "id": 321250,
          "rating": 2,
          "media": {
            "id": 696,
            "title": {
              "native": "天地無用！"
            }
          },
          "mediaRecommendation": {
            "id": 20057,
            "title": {
              "native": "スペース☆ダンディ"
            }
          }
        }
      },
      {
        "node": {
          "id": 321695,
          "rating": 2,
          "media": {
            "id": 696,
            "title": {
              "native": "天地無用！"
            }
          },
          "mediaRecommendation": {
            "id": 568,
            "title": {
              "native": "バブルガムクライシス TOKYO2040"
            }
          }
        }
      },
      {
        "node": {
          "id": 322259,
          "rating": 3,
          "media": {
            "id": 696,
            "title": {
              "native": "天地無用！"
            }
          },
          "mediaRecommendation": {
            "id": 1658,
            "title": {
              "native": "からくりの君"
            }
          }
        }
      },
      {
        "node": {
          "id": 322261,
          "rating": 1,
          "media": {
            "id": 696,
            "title": {
              "native": "天地無用！"
            }
          },
          "mediaRecommendation": {
            "id": 45,
            "title": {
              "native": "るろうに剣心 -明治剣客浪漫譚-"
            }
          }
        }
      },
      {
        "node": {
          "id": 322264,
          "rating": 1,
          "media": {
            "id": 696,
            "title": {
              "native": "天地無用！"
            }
          },
          "mediaRecommendation": {
            "id": 117,
            "title": {
              "native": "神秘の世界エルハザード"
            }
          }
        }
      },
      {
        "node": {
          "id": 323280,
          "rating": 2,
          "media": {
            "id": 696,
            "title": {
              "native": "天地無用！"
            }
          },
          "mediaRecommendation": {
            "id": 4999,
            "title": {
              "native": "明日のよいち！"
            }
          }
        }
      },
      {
        "node": {
          "id": 333771,
          "rating": 1,
          "media": {
            "id": 696,
            "title": {
              "native": "天地無用！"
            }
          },
          "mediaRecommendation": {
            "id": 17505,
            "title": {
              "native": "ムシブギョー"
            }
          }
        }
      },
      {
        "node": {
          "id": 333774,
          "rating": 2,
          "media": {
            "id": 696,
            "title": {
              "native": "天地無用！"
            }
          },
          "mediaRecommendation": {
            "id": 1264,
            "title": {
              "native": "鎧伝サムライトルーパー"
            }
          }
        }
      }
    ]
  },
  "stats": {
    "scoreDistribution": [
      {
        "score": 10,
        "amount": 29
      },
      {
        "score": 20,
        "amount": 19
      },
      {
        "score": 30,
        "amount": 66
      },
      {
        "score": 40,
        "amount": 99
      },
      {
        "score": 50,
        "amount": 316
      },
      {
        "score": 60,
        "amount": 616
      },
      {
        "score": 70,
        "amount": 1234
      },
      {
        "score": 80,
        "amount": 866
      },
      {
        "score": 90,
        "amount": 563
      },
      {
        "score": 100,
        "amount": 313
      }
    ],
    "statusDistribution": [
      {
        "status": "CURRENT",
        "amount": 761
      },
      {
        "status": "PLANNING",
        "amount": 7669
      },
      {
        "status": "COMPLETED",
        "amount": 6575
      },
      {
        "status": "DROPPED",
        "amount": 402
      },
      {
        "status": "PAUSED",
        "amount": 468
      }
    ]
  },
  "siteUrl": "https://anilist.co/anime/696",
  "modNotes": null
}